pylambertw/__init__.py
pylambertw/lamberter.py
pylambertw/tukeyhutils.py
pylambertw-0.0.1.data/scripts/simulate_heavytails
pylambertw-0.0.1.dist-info/METADATA
pylambertw-0.0.1.dist-info/WHEEL
pylambertw-0.0.1.dist-info/top_level.txt
pylambertw-0.0.1.dist-info/RECORD
